good/__init__.py
good/girl/__init__.py
good/girl/messgers.py
gjy-0.3.dist-info/METADATA
gjy-0.3.dist-info/WHEEL
gjy-0.3.dist-info/top_level.txt
gjy-0.3.dist-info/RECORD
