Metadata-Version: 2.1
Name: gjy
Version: 0.3
Summary: 郭洁迎
Author: gjy
License: UNKNOWN
Platform: UNKNOWN
